keywads/__init__.py
keywads/keyword_analyzer.py
keywads/source_file_transformer.py
keywads-0.1.5.dist-info/LICENSE
keywads-0.1.5.dist-info/METADATA
keywads-0.1.5.dist-info/WHEEL
keywads-0.1.5.dist-info/top_level.txt
keywads-0.1.5.dist-info/RECORD
