Metadata-Version: 2.1
Name: keywads
Version: 0.1.5
Summary: A Python package for keyword analysis from Excel files.
Home-page: https://github.com/hashangit/keywads
Author: Hashan Wickramasinghe
Author-email: hashanwickramasinghe@gmail.com
Classifier: Programming Language :: Python :: 3
Classifier: License :: OSI Approved :: MIT License
Classifier: Operating System :: OS Independent
Requires-Python: >=3.6
License-File: LICENSE
Requires-Dist: pandas >=1.0.0
